simple_port_checker/__init__.py
simple_port_checker/__main__.py
simple_port_checker/cli.py
simple_port_checker/py.typed
simple_port_checker/core/__init__.py
simple_port_checker/core/cert_analyzer.py
simple_port_checker/core/hybrid_identity_checker.py
simple_port_checker/core/l7_detector.py
simple_port_checker/core/mtls_checker.py
simple_port_checker/core/owasp_scanner.py
simple_port_checker/core/port_scanner.py
simple_port_checker/core/security_headers.py
simple_port_checker/models/__init__.py
simple_port_checker/models/l7_result.py
simple_port_checker/models/mtls_result.py
simple_port_checker/models/owasp_result.py
simple_port_checker/models/scan_result.py
simple_port_checker/utils/__init__.py
simple_port_checker/utils/common_ports.py
simple_port_checker/utils/exporters.py
simple_port_checker/utils/l7_signatures.py
simple_port_checker/utils/owasp_remediation.py
simple_port_checker-1.1.2.dist-info/METADATA
simple_port_checker-1.1.2.dist-info/WHEEL
simple_port_checker-1.1.2.dist-info/entry_points.txt
simple_port_checker-1.1.2.dist-info/licenses/LICENSE
simple_port_checker-1.1.2.dist-info/RECORD
