Metadata-Version: 2.4
Name: simple-port-checker
Version: 1.1.2
Summary: A comprehensive tool for checking firewall ports, L7 protection services, SSL/TLS certificate analysis, and OWASP Top 10 vulnerability scanning
Project-URL: Homepage, https://github.com/htunn/simple-port-checker
Project-URL: Repository, https://github.com/htunn/simple-port-checker
Project-URL: Issues, https://github.com/htunn/simple-port-checker/issues
Project-URL: Documentation, https://github.com/htunn/simple-port-checker#readme
Author-email: htunn <htunnthuthu.linux@gmail.com>
Maintainer-email: htunn <htunnthuthu.linux@gmail.com>
License: MIT
License-File: LICENSE
Keywords: certificate,certificate-analysis,firewall,l7-protection,network,pki,port-scanner,security,ssl,tls,waf
Classifier: Development Status :: 4 - Beta
Classifier: Intended Audience :: Developers
Classifier: Intended Audience :: System Administrators
Classifier: License :: OSI Approved :: MIT License
Classifier: Operating System :: OS Independent
Classifier: Programming Language :: Python :: 3
Classifier: Programming Language :: Python :: 3.12
Classifier: Topic :: Internet
Classifier: Topic :: Security
Classifier: Topic :: System :: Networking
Classifier: Topic :: System :: Systems Administration
Requires-Python: >=3.12
Requires-Dist: aiohttp>=3.9.0
Requires-Dist: asyncio-throttle>=1.0.2
Requires-Dist: brotli>=1.0.9
Requires-Dist: click>=8.1.0
Requires-Dist: cryptography>=41.0.0
Requires-Dist: dnspython>=2.4.0
Requires-Dist: pydantic>=2.0.0
Requires-Dist: python-nmap>=0.7.1
Requires-Dist: requests>=2.31.0
Requires-Dist: rich>=13.0.0
Provides-Extra: dev
Requires-Dist: black>=23.0.0; extra == 'dev'
Requires-Dist: flake8>=6.0.0; extra == 'dev'
Requires-Dist: isort>=5.12.0; extra == 'dev'
Requires-Dist: mypy>=1.5.0; extra == 'dev'
Requires-Dist: pre-commit>=3.4.0; extra == 'dev'
Requires-Dist: pytest-asyncio>=0.21.0; extra == 'dev'
Requires-Dist: pytest-cov>=4.1.0; extra == 'dev'
Requires-Dist: pytest>=7.4.0; extra == 'dev'
